confluent_cloud_sdk/__init__.py
confluent_cloud_sdk/client_factory.py
confluent_cloud_sdk/confluent_cloud_api/__init__.py
confluent_cloud_sdk/confluent_cloud_api/cluster_v2.py
confluent_cloud_sdk/confluent_cloud_api/environmentv2.py
confluent_cloud_sdk/confluent_cloud_api/iam_v2_apikey.py
confluent_cloud_sdk/confluent_cloud_api/iam_v2_serviceaccount.py
confluent_cloud_sdk/confluent_cluster_v2.py
confluent_cloud_sdk/confluent_iam_v2.py
confluent_cloud_sdk/confluent_org_v2.py
confluent_cloud_sdk/errors.py
confluent_cloud_sdk-0.2.3.dist-info/LICENSE
confluent_cloud_sdk-0.2.3.dist-info/METADATA
confluent_cloud_sdk-0.2.3.dist-info/WHEEL
confluent_cloud_sdk-0.2.3.dist-info/RECORD
