Metadata-Version: 2.1
Name: confluent-cloud-sdk
Version: 0.2.3
Summary: Confluent Cloud API SDK
License: GPL-2-only
Keywords: kafka,confluent,sdk
Author: John Preston
Author-email: john@ews-network.net
Requires-Python: >=3.8,<4.0
Classifier: Development Status :: 4 - Beta
Classifier: Intended Audience :: Developers
Classifier: License :: OSI Approved :: GNU General Public License v2 (GPLv2)
Classifier: License :: Other/Proprietary License
Classifier: Natural Language :: English
Classifier: Programming Language :: Python :: 3
Classifier: Programming Language :: Python :: 3.8
Classifier: Programming Language :: Python :: 3.9
Classifier: Programming Language :: Python :: 3.10
Classifier: Programming Language :: Python :: 3.11
Requires-Dist: compose-x-common (>=1.4,<2.0)
Requires-Dist: pydantic (>=1.10.2,<2.0.0)
Requires-Dist: requests (>=2.27.1,<3.0.0)
Project-URL: Bug Tracker, https://codeberg.org/compose-x/confluent-cloud-sdk/issues
Project-URL: Confluent API Documentation, https://docs.confluent.io/cloud/current/api.html
